robcointeg/__init__.py
robcointeg/core.py
robcointeg/critical_values.py
robcointeg/diagnostics.py
robcointeg/tests.py
robcointeg/utils.py
robcointeg/weights.py
robcointeg/data/__init__.py
robcointeg-0.0.2.dist-info/licenses/LICENSE
robcointeg-0.0.2.dist-info/METADATA
robcointeg-0.0.2.dist-info/WHEEL
robcointeg-0.0.2.dist-info/top_level.txt
robcointeg-0.0.2.dist-info/RECORD
