Metadata-Version: 2.4
Name: robcointeg
Version: 0.0.2
Summary: Outlier-Robust Cointegration Analysis based on Franses & Lucas (1998)
Author-email: Dr Merwan Roudane <merwanroudane920@gmail.com>
License: MIT
Project-URL: Homepage, https://github.com/merwanroudane/robcointeg
Project-URL: Documentation, https://github.com/merwanroudane/robcointeg#readme
Project-URL: Repository, https://github.com/merwanroudane/robcointeg
Project-URL: Issues, https://github.com/merwanroudane/robcointeg/issues
Keywords: cointegration,robust statistics,outlier detection,time series,econometrics,unit root,VAR,VECM,Johansen test,Student-t,pseudolikelihood
Classifier: Development Status :: 3 - Alpha
Classifier: Intended Audience :: Science/Research
Classifier: Intended Audience :: Financial and Insurance Industry
Classifier: License :: OSI Approved :: MIT License
Classifier: Operating System :: OS Independent
Classifier: Programming Language :: Python :: 3
Classifier: Programming Language :: Python :: 3.8
Classifier: Programming Language :: Python :: 3.9
Classifier: Programming Language :: Python :: 3.10
Classifier: Programming Language :: Python :: 3.11
Classifier: Programming Language :: Python :: 3.12
Classifier: Topic :: Scientific/Engineering :: Mathematics
Classifier: Topic :: Scientific/Engineering :: Information Analysis
Classifier: Topic :: Office/Business :: Financial :: Investment
Requires-Python: >=3.8
License-File: LICENSE
Requires-Dist: numpy>=1.20.0
Requires-Dist: scipy>=1.7.0
Provides-Extra: plotting
Requires-Dist: matplotlib>=3.4.0; extra == "plotting"
Provides-Extra: full
Requires-Dist: matplotlib>=3.4.0; extra == "full"
Requires-Dist: pandas>=1.3.0; extra == "full"
Provides-Extra: dev
Requires-Dist: pytest>=7.0.0; extra == "dev"
Requires-Dist: pytest-cov>=3.0.0; extra == "dev"
Requires-Dist: black>=22.0.0; extra == "dev"
Requires-Dist: flake8>=4.0.0; extra == "dev"
Requires-Dist: mypy>=0.950; extra == "dev"
Provides-Extra: docs
Requires-Dist: sphinx>=4.0.0; extra == "docs"
Requires-Dist: sphinx-rtd-theme>=1.0.0; extra == "docs"
Requires-Dist: numpydoc>=1.2.0; extra == "docs"
Dynamic: license-file
